README.md
zmag-0.1.2.dist-info/METADATA
zmag-0.1.2.dist-info/WHEEL
zmag-0.1.2.dist-info/entry_points.txt
zmag-0.1.2.dist-info/licenses/LICENSE
zmag/__about__.py
zmag/__init__.py
zmag/external.py
zmag/framework/__init__.py
zmag/framework/apps_templates/base_app.zip
zmag/framework/commands/__init__.py
zmag/framework/commands/cli.py
zmag/framework/commands/core_commands.py
zmag/framework/commands/keypair.py
zmag/framework/commands/shell.py
zmag/framework/commands/start_app.py
zmag/framework/commands/unzipper.py
zmag/framework/commands/utils.py
zmag/framework/components/__init__.py
zmag/framework/components/base.py
zmag/framework/components/commands.py
zmag/framework/components/forms.py
zmag/framework/components/graphql.py
zmag/framework/components/handlers/__init__.py
zmag/framework/components/handlers/graphql/__init__.py
zmag/framework/components/handlers/graphql/base.py
zmag/framework/components/handlers/graphql/schema.py
zmag/framework/components/handlers/utils.py
zmag/framework/components/network.py
zmag/framework/components/objects.py
zmag/framework/framework.py
zmag/framework/services/__init__.py
zmag/framework/services/debugger.py
zmag/framework/services/pub_push.py
zmag/framework/services/queue.py
zmag/framework/services/runner.py
zmag/framework/services/watcher.py
zmag/graphql/__init__.py
zmag/graphql/inputs.py
zmag/graphql/types.py
zmag/network/__init__.py
zmag/network/base.py
zmag/network/keypair.py
zmag/network/utils.py
zmag/py.typed
zmag/tools/__init__.py
zmag/tools/coro.py
zmag/tools/datetime.py
zmag/tools/generic.py
zmag/tools/text.py
zmag/tools/timer.py
zmag/types.py
zmag_installer.py
zmag-0.1.2.dist-info/RECORD
