Metadata-Version: 2.1
Name: zmag
Version: 0.1.2
Summary: Craft Network APIs with ZeroMQ and GraphQL
Author-Email: hlop3z <23062270+hlop3z@users.noreply.github.com>
License: MIT
Requires-Python: >=3.12
Requires-Dist: pyzmq>=26.2.0
Requires-Dist: orjson>=3.10.7
Provides-Extra: debug
Requires-Dist: uvicorn[standard]>=0.30.6; extra == "debug"
Requires-Dist: starlette>=0.38.2; extra == "debug"
Requires-Dist: watchdog>=4.0.2; extra == "debug"
Provides-Extra: server
Requires-Dist: spoc>=0.2.2; extra == "server"
Requires-Dist: strawberry-graphql>=0.237.3; extra == "server"
Requires-Dist: click>=8.1.7; extra == "server"
Requires-Dist: click-help-colors>=0.9.4; extra == "server"
